{
  "$schema": "http://json-schema.org/draft-04/schema#",
  "description": "A collection of service points",
  "type": "object",
  "properties": {
    "servicepoints": {
      "description": "List of service points",
      "id": "servicepoint",
      "type": "array",
      "items": {
        "type": "object",
        "$ref": "servicepoint.json"
      }
    },
    "totalRecords": {
      "description": "Estimated or exact total number of records",
      "type": "integer"
    }
  },
  "required": [
    "servicepoints",
    "totalRecords"
  ]
}
